Workbook

Sheet 测试计划
A1: 智能商城软件测试计划
A2: 参考模板：软件测试表格模板包.xlsx（14 个页签：说明与目录、字典、测试计划、需求跟踪矩阵、测试用例、执行记录、缺陷登记、环境与账号、测试数据、兼容性矩阵、风险问题、自动化清单、测试报告、发布检查清单）；本交付仅保留六个必需页签
A4: 1. 基本信息
A5: 项目名称 | B5: 智能商城（淘宝 + AI 助手微型生态闭环） | E5: 测试版本 | F5: 当前工作区 / 2026-07-12
A6: 测试周期 | B6: 2026-07-12 | E6: 测试负责人 | F6: Codex 执行，项目组复核
A7: 测试环境 | B7: Docker Compose 本机集成环境 | E7: 测试结论口径 | F7: 严格按首轮结果；复测单独说明
A8: 依据 | B8: AGENTS.md、源码、接口、运行日志和浏览器操作 | E8: 数据策略 | F8: 保留脚本生成的隔离夹具，不重置共享卷
A10: 2. 测试范围
A11: 范围 | B11: 模块 | C11: 核心内容 | D11: 主要风险 | E11: 本轮方法
A12: 范围内 | B12: 用户模块 | C12: 注册、登录、JWT、Refresh、个人资料、ADMIN 权限 | D12: 认证旁路、错误码不一致、密码存储 | E12: JUnit/RestAssured + REST + 浏览器
A13: 范围内 | B13: 商品与搜索 | C13: 分类、CRUD、分页、排序、模糊搜索、图片上传 | D13: 边界参数、搜索排序、库存状态 | E13: 集成测试 + REST + 浏览器 + 静态审计
A14: 范围内 | B14: 购物车与订单 | C14: 加购、结算、下单、状态机、库存回补、事务 | D14: 超卖、脏数据、主链路阻断 | E14: JUnit + 真实 MySQL 并发 + 浏览器
A15: 范围内 | B15: AI 助手 | C15: 工具调用、订单查询、短期/长期记忆、拒答 | D15: LLM 不确定性、跨会话污染、身份边界 | E15: 真实模型烟测 + REST + 浏览器 + 代码审计
A16: 范围内 | B16: 部署与数据库 | C16: Compose、健康检查、日志、Schema/Seed、ER 文档 | D16: 全新环境复现、端口与文档口径 | E16: Compose/日志/SQL/文档检查
A17: 范围外 | B17: 明确排除项 | C17: 真实支付、OAuth、复杂 RBAC、多 SKU、MQ、网关、移动端 | D17: 避免超出教学大纲 | E17: 不执行，仅确认未误纳入验收
A19: 3. 测试策略与准入/准出
A20: 测试类型 | B20: 目标 | C20: 执行方式 | D20: 工具/证据 | E20: 通过标准
A21: 单元/集成 | B21: 用户、购物车、订单、优惠券、售后 | C21: 执行后端 Maven 测试 | D21: JUnit5、Mockito、H2、RestAssured | E21: 全部测试 0 failures / 0 errors
A22: 接口测试 | B22: 鉴权、错误码、分页、状态机 | C22: 调用本地 8081/8000 接口 | D22: PowerShell/curl、应用日志 | E22: 状态码、响应体和数据副作用符合规格
A23: 并发测试 | B23: 100 请求竞争 80 库存 | C23: 创建隔离用户和商品后并发直购 | D23: scripts/concurrent_order_test.py | E23: 成功 80、库存不足 20、stock=0、无异常
A24: AI 烟测 | B24: 工具、订单、记忆、确认加购、拒答 | C24: 调用真实模型和真实后端 | D24: scripts/agent_smoke.py | E24: 所有断言通过；首轮异常单独登记
A25: 浏览器测试 | B25: 登录、搜索、购物车、结算、订单、AI | C25: Codex 应用内浏览器点击验证 | D25: DOM 快照、控制台日志 | E25: 页面可见且无阻断脚本错误
A26: 静态合规 | B26: 事务注解、权限边界、ER、Seed、环境变量 | C26: 源码与文档核对 | D26: rg、代码审计 | E26: 满足 AGENTS.md 明确验收条款
A27: 部署验证 | B27: 一键启动、健康检查、日志 | C27: 检查 Compose 和容器状态 | D27: Docker 29.6.1 / Compose 5.2.0 | E27: 四服务 healthy，日志无 ERROR
A29: 4. 测试安排
A30: 阶段 | B30: 日期 | C30: 工作内容 | D30: 产出 | E30: 责任
A31: 准备 | B31: 2026-07-12 | C31: 盘点需求、环境、账号、Seed 和测试入口 | D31: 范围与环境清单 | E31: Codex
A32: 自动化 | B32: 2026-07-12 | C32: 后端 30 测试、前端构建、Agent 烟测 | D32: 执行记录和日志 | E32: Codex
A33: 运行态 | B33: 2026-07-12 | C33: REST 主链路、100/80 并发、容器健康 | D33: 接口与并发证据 | E33: Codex
A34: 浏览器 | B34: 2026-07-12 | C34: 登录、搜索、购物车、结算、订单和 AI | D34: 可见流程证据 | E34: Codex
A35: 报告 | B35: 2026-07-12 | C35: 汇总用例、缺陷、风险和准出结论 | D35: 本工作簿 | E35: Codex / 项目组复核
A37: 5. 准入、准出与风险
A38: 类别 | B38: 条件 | C38: 本轮状态 | D38: 说明
A39: 准入 | B39: .env 已配置必要密钥且四服务可启动 | C39: 通过 | D39: 未记录或泄露任何密钥值
A40: 准入 | B40: 基础 Seed 与测试账号可用 | C40: 通过 | D40: admin/alice/bob 均可登录
A41: 准出 | B41: 后端自动化全部通过 | C41: 通过 | D41: 30/30，0 failures，0 errors
A42: 准出 | B42: 100 并发不超卖 | C42: 通过 | D42: 成功 80、库存不足 20、最终库存 0
A43: 准出 | B43: 五大模块主链路可浏览器演示 | C43: 失败 | D43: 结算页 reactive 未导入导致空白
A44: 准出 | B44: 阻断和高严重度缺陷清零 | C44: 失败 | D44: 存在结算阻断、跨会话加购和聊天隔离问题
A45: 风险 | B45: 真实 LLM 工具选择具有非确定性 | C45: 存在 | D45: compare_products 首轮遗漏，复测通过
A46: 风险 | B46: 共享 MySQL 卷不是全新基线 | C46: 存在 | D46: 未执行破坏性重置；全新卷初始化待补测
A47: 风险 | B47: 前端和 Agent 缺少确定性自动化 | C47: 存在 | D47: 前端无 test 脚本，pytest 收集 0 项

Sheet 测试用例
A1: 智能商城测试用例表
A2: 结果来自 2026-07-12 自动化、REST、并发、浏览器和静态审计；失败项均关联缺陷
A4: 用例ID | B4: 模块 | C4: 测试点 | D4: 优先级 | E4: 类型 | F4: 前置条件 | G4: 操作步骤 | H4: 测试数据 | I4: 预期结果 | J4: 实际结果 | K4: 结果 | L4: 关联缺陷 | M4: 执行方式/证据 | N4: 执行日期
A5: TC-AUTH-001 | B5: 用户模块 | C5: 未登录访问个人资料 | D5: P0 | E5: 安全/接口 | F5: 服务健康 | G5: GET /api/user/profile，不携带 Token | H5: 无 | I5: 返回 401 | J5: HTTP 401 | K5: 通过 | M5: REST 实测 | N5: 2026-07-12
A6: TC-AUTH-002 | B6: 用户模块 | C6: 正确账号登录 | D6: P0 | E6: 功能/接口 | F6: Seed 已加载 | G6: POST /api/auth/login | H6: alice / 123456 | I6: 返回 accessToken、refreshToken 和用户信息 | J6: HTTP 200，Token 字段完整 | K6: 通过 | M6: REST + 浏览器 | N6: 2026-07-12
A7: TC-AUTH-003 | B7: 用户模块 | C7: 错误密码统一提示 | D7: P0 | E7: 安全/接口 | F7: 用户存在 | G7: 使用错误密码登录 | H7: alice / wrong-password | I7: 返回 401 且不区分用户是否存在 | J7: HTTP 401，消息“用户名或密码错误” | K7: 通过 | M7: REST 实测 | N7: 2026-07-12
A8: TC-AUTH-004 | B8: 用户模块 | C8: Refresh Token 换取 Access Token | D8: P0 | E8: 接口 | F8: 已登录 | G8: POST /api/auth/refresh | H8: 有效 refreshToken | I8: 返回新的 accessToken | J8: HTTP 200 | K8: 通过 | M8: REST 实测 | N8: 2026-07-12
A9: TC-AUTH-005 | B9: 用户模块 | C9: 重复用户名注册 | D9: P1 | E9: 边界/接口 | F9: alice 已存在 | G9: POST /api/auth/register | H9: username=alice | I9: 返回 409 | J9: HTTP 409 | K9: 通过 | M9: REST 实测 | N9: 2026-07-12
A10: TC-AUTH-006 | B10: 用户模块 | C10: 短密码校验 | D10: P1 | E10: 边界/接口 | F10: 无 | G10: 注册密码少于 6 位 | H10: password=12345 | I10: 返回 400 | J10: HTTP 400 | K10: 通过 | M10: REST 实测 | N10: 2026-07-12
A11: TC-AUTH-007 | B11: 用户模块 | C11: 注册缺失 password | D11: P0 | E11: 异常/接口 | F11: 无 | G11: 注册请求不传 password | H11: 仅 username、phone | I11: 返回 400 参数错误 | J11: passwordEncoder.encode(null) 导致 HTTP 500 | K11: 失败 | L11: D-003 | M11: REST + 源码审计 | N11: 2026-07-12
A12: TC-AUTH-008 | B12: 用户模块 | C12: 普通用户创建商品 | D12: P0 | E12: 权限/接口 | F12: alice 已登录 | G12: POST /api/products | H12: 合法商品请求体 | I12: 返回 403 | J12: HTTP 403 | K12: 通过 | M12: REST 实测 | N12: 2026-07-12
A13: TC-AUTH-009 | B13: 用户模块 | C13: 管理员访问后台 | D13: P0 | E13: 权限/浏览器 | F13: admin 已登录 | G13: 登录后进入 /admin | H13: admin / 123456 | I13: 后台可访问，ADMIN 权限生效 | J13: 后端权限与管理员登录通过 | K13: 通过 | M13: REST + 源码审计 | N13: 2026-07-12
A14: TC-AUTH-010 | B14: 用户模块 | C14: 匿名访问管理员商品列表 | D14: P0 | E14: 安全/接口 | F14: 未登录 | G14: GET /api/products/admin | H14: 无 Token | I14: 按项目要求返回 401 | J14: 实际返回 403 | K14: 失败 | L14: D-002 | M14: REST 实测 | N14: 2026-07-12
A15: TC-AUTH-011 | B15: 用户模块 | C15: 密码 BCrypt 存储 | D15: P0 | E15: 安全/单元 | F15: Seed/注册可用 | G15: 检查密码编码与匹配 | H15: 123456 | I15: 哈希以 $2a$10$ 开头，错误密码不匹配 | J15: PasswordEncoderTest 通过，Seed 为 $2a$10$ | K15: 通过 | M15: JUnit + SQL 审计 | N15: 2026-07-12
A16: TC-PROD-001 | B16: 商品与搜索 | C16: 分类树查询 | D16: P1 | E16: 功能/接口 | F16: 服务健康 | G16: GET /api/categories | H16: 无 | I16: 返回顶级分类及 children | J16: HTTP 200，7 个顶级分类 | K16: 通过 | M16: REST 实测 | N16: 2026-07-12
A17: TC-PROD-002 | B17: 商品与搜索 | C17: 商品列表分页 | D17: P0 | E17: 功能/接口 | F17: 有商品数据 | G17: GET /api/products?page=1&size=3 | H17: page=1,size=3 | I17: 返回 total 和 3 条 list | J17: HTTP 200，total=65（执行时） | K17: 通过 | M17: REST 实测 | N17: 2026-07-12
A18: TC-PROD-003 | B18: 商品与搜索 | C18: 中文模糊搜索 | D18: P0 | E18: 功能/接口 | F18: Seed 已加载 | G18: 搜索“键盘” | H18: keyword=键盘 | I18: 命中名称或描述含关键字商品 | J18: HTTP 200，total=5 | K18: 通过 | M18: REST + 浏览器 | N18: 2026-07-12
A19: TC-PROD-004 | B19: 商品与搜索 | C19: 页码超过最大页 | D19: P1 | E19: 边界/接口 | F19: 有商品数据 | G19: GET page=999 | H19: page=999 | I19: 返回空列表，不报错 | J19: HTTP 200，list=[] | K19: 通过 | M19: REST 实测 | N19: 2026-07-12
A20: TC-PROD-005 | B20: 商品与搜索 | C20: 查询不存在商品 | D20: P1 | E20: 异常/接口 | F20: 无 | G20: GET /api/products/999999999 | H20: 不存在 ID | I20: 返回 404 | J20: HTTP 404 | K20: 通过 | M20: REST 实测 | N20: 2026-07-12
A21: TC-PROD-006 | B21: 商品与搜索 | C21: 销量优先展示 | D21: P2 | E21: 功能/浏览器 | F21: 首页可用 | G21: 打开商品页观察默认排序 | H21: 无 | I21: 高销量商品优先 | J21: 首页首屏显示高销量商品 | K21: 通过 | M21: 浏览器实测 | N21: 2026-07-12
A22: TC-PROD-007 | B22: 商品与搜索 | C22: 搜索结果价格排序 | D22: P1 | E22: 功能/前端 | F22: 处于关键词搜索 | G22: 切换价格升序/降序 | H22: keyword=键盘 | I22: 请求携带 sort 且顺序变化 | J22: 搜索请求未传 sort，控件不生效 | K22: 失败 | L22: D-008 | M22: 源码审计 | N22: 2026-07-12
A23: TC-PROD-008 | B23: 商品与搜索 | C23: 搜索关键字前后空格 | D23: P2 | E23: 边界/接口 | F23: 有键盘商品 | G23: 搜索“ 键盘 ” | H23: keyword=%20键盘%20 | I23: 服务端 trim 后仍命中 5 条 | J23: 实际 total=0 | K23: 失败 | L23: D-015 | M23: REST 实测 | N23: 2026-07-12
A24: TC-PROD-009 | B24: 商品与搜索 | C24: 商品价格必须为正数 | D24: P0 | E24: 校验/接口 | F24: admin 已登录 | G24: 创建 price<=0 商品 | H24: price=0 | I24: 返回 400 | J24: BusinessFlowHttpIntegrationTest 通过 | K24: 通过 | M24: RestAssured | N24: 2026-07-12
A25: TC-PROD-010 | B25: 商品与搜索 | C25: 商品库存不得为负 | D25: P0 | E25: 校验/接口 | F25: admin 已登录 | G25: 创建 stock<0 商品 | H25: stock=-1 | I25: 返回 400 | J25: BusinessFlowHttpIntegrationTest 通过 | K25: 通过 | M25: RestAssured | N25: 2026-07-12
A26: TC-PROD-011 | B26: 商品与搜索 | C26: 本地图片上传与读取 | D26: P1 | E26: 功能/接口 | F26: admin 已登录 | G26: 上传 PNG 并读取返回 URL | H26: cover.png | I26: 201 且 /uploads/** 可访问 | J26: 自动化回归通过 | K26: 通过 | M26: RestAssured | N26: 2026-07-12
A27: TC-PROD-012 | B27: 商品与搜索 | C27: 非法分页和路径参数 | D27: P1 | E27: 异常/接口 | F27: 服务健康 | G27: 请求 page=abc 与 /products/not-a-number | H27: 非法字符串 | I27: 返回 400 | J27: 两种请求均返回 500 | K27: 失败 | L27: D-003 | M27: REST 实测 | N27: 2026-07-12
A28: TC-CART-001 | B28: 购物车 | C28: 未登录访问购物车 | D28: P0 | E28: 安全/接口 | F28: 未登录 | G28: GET /api/cart | H28: 无 | I28: 返回 401 | J28: HTTP 401 | K28: 通过 | M28: REST 实测 | N28: 2026-07-12
A29: TC-CART-002 | B29: 购物车 | C29: 加入购物车 | D29: P0 | E29: 功能/接口 | F29: 测试用户已登录 | G29: POST /api/cart | H29: productId=21,quantity=1 | I29: 201，购物车新增商品 | J29: HTTP 201 | K29: 通过 | M29: 隔离业务链路 | N29: 2026-07-12
A30: TC-CART-003 | B30: 购物车 | C30: 重复商品数量合并 | D30: P1 | E30: 功能/集成 | F30: 购物车已有同商品 | G30: 再次加购同一商品 | H30: 相同 productId | I30: 保持 user+product 唯一并更新数量 | J30: CartControllerIntegrationTest 通过 | K30: 通过 | M30: JUnit 集成测试 | N30: 2026-07-12
A31: TC-CART-004 | B31: 购物车 | C31: 数量为 0 或负数 | D31: P1 | E31: 边界/接口 | F31: 已登录 | G31: 新增/更新非法数量 | H31: quantity=0/-1 | I31: 返回 400 | J31: 校验测试通过 | K31: 通过 | M31: JUnit/REST | N31: 2026-07-12
A32: TC-CART-005 | B32: 购物车 | C32: 缺失 quantity | D32: P0 | E32: 异常/接口 | F32: 已登录 | G32: POST /api/cart 不传 quantity | H32: 仅 productId | I32: 返回 400 | J32: 空值拆箱导致 HTTP 500 | K32: 失败 | L32: D-003 | M32: REST + 源码审计 | N32: 2026-07-12
A33: TC-CART-006 | B33: 购物车 | C33: 数量超过库存 | D33: P0 | E33: 业务/接口 | F33: 库存有限 | G33: 加购数量大于库存 | H33: quantity=stock+1 | I33: 返回明确库存不足 | J33: CartControllerIntegrationTest 通过 | K33: 通过 | M33: JUnit 集成测试 | N33: 2026-07-12
A34: TC-CART-007 | B34: 购物车 | C34: 购物车合计实时计算 | D34: P1 | E34: 功能/浏览器 | F34: alice 有 2 个购物车项 | G34: 打开 /cart | H34: 129x2 + 399x1 | I34: 显示 2 件、合计 ¥657 | J34: 浏览器显示 ¥657.00 | K34: 通过 | M34: 浏览器实测 | N34: 2026-07-12
A35: TC-CART-008 | B35: 购物车 | C35: 售罄商品禁止加购 | D35: P0 | E35: 前端/浏览器 | F35: 存在 stock=0 测试商品 | G35: 查看推荐和商品卡 | H35: 并发测试商品 stock=0 | I35: 按钮禁用 | J35: 浏览器按钮 disabled | K35: 通过 | M35: 浏览器实测 | N35: 2026-07-12
A36: TC-ORDER-001 | B36: 订单模块 | C36: 购物车创建订单 | D36: P0 | E36: 主链路/接口 | F36: 隔离用户购物车有商品 | G36: POST /api/orders | H36: cartItemIds + 地址 | I36: 201，PENDING_PAYMENT | J36: 订单 377 创建成功 | K36: 通过 | M36: 隔离 REST 链路 | N36: 2026-07-12
A37: TC-ORDER-002 | B37: 订单模块 | C37: 空收货地址校验 | D37: P0 | E37: 边界/接口 | F37: 已登录 | G37: 创建订单时地址为空 | H37: shippingAddress="" | I37: 返回 400 | J37: HTTP 400 | K37: 通过 | M37: REST 实测 | N37: 2026-07-12
A38: TC-ORDER-003 | B38: 订单模块 | C38: 浏览器进入结算页 | D38: P0 | E38: 主链路/浏览器 | F38: alice 购物车有商品 | G38: /cart 点击“去结算” | H38: cartItemIds=2,1 | I38: 显示商品、优惠、地址和提交按钮 | J38: 路由跳转后页面空白，reactive 未定义 | K38: 失败 | L38: D-001 | M38: 浏览器控制台 + CheckoutView.vue:118/136 | N38: 2026-07-12
A39: TC-ORDER-004 | B39: 订单模块 | C39: 待付款直接确认收货 | D39: P0 | E39: 状态机/接口 | F39: 订单为 PENDING_PAYMENT | G39: PUT /confirm | H39: orderId=377 | I39: 拒绝非法跳转，返回 400 | J39: HTTP 400 | K39: 通过 | M39: 隔离 REST 链路 | N39: 2026-07-12
A40: TC-ORDER-005 | B40: 订单模块 | C40: 取消待付款订单 | D40: P0 | E40: 状态机/接口 | F40: 订单为 PENDING_PAYMENT | G40: PUT /cancel | H40: orderId=377 | I40: 订单变为 CANCELLED | J40: HTTP 200，状态 CANCELLED | K40: 通过 | M40: 隔离 REST 链路 | N40: 2026-07-12
A41: TC-ORDER-006 | B41: 订单模块 | C41: 取消订单回补库存 | D41: P0 | E41: 事务/接口 | F41: 订单已扣库存 | G41: 取消后查询商品 | H41: productId=21 | I41: 库存恢复至下单前 | J41: 80 -> 扣减 -> 80 | K41: 通过 | M41: REST + 数据校验 | N41: 2026-07-12
A42: TC-ORDER-007 | B42: 订单模块 | C42: 下单后清理购物车 | D42: P1 | E42: 事务/接口 | F42: 从购物车下单 | G42: 下单后查询购物车 | H42: 测试购物车项 | I42: 对应项被删除 | J42: 隔离链路确认已清空 | K42: 通过 | M42: REST 实测 | N42: 2026-07-12
A43: TC-ORDER-008 | B43: 订单模块 | C43: 100 请求竞争 80 库存 | D43: P0 | E43: 并发/数据库 | F43: 真实 MySQL，隔离商品库存80 | G43: 运行 concurrent_order_test.py | H43: requests=100,stock=80 | I43: 成功80、库存不足20、无异常 | J43: 80/20/0，耗时约3084ms | K43: 通过 | M43: 真实 MySQL 并发 | N43: 2026-07-12
A44: TC-ORDER-009 | B44: 订单模块 | C44: 并发后库存/销量/version | D44: P0 | E44: 并发/数据库 | F44: 并发用例完成 | G44: 查询并发商品 | H44: productId=66 | I44: stock=0,sales=80,version=80 | J44: 实际 0/80/80 | K44: 通过 | M44: 脚本断言 + 数据校验 | N44: 2026-07-12
A45: TC-ORDER-010 | B45: 订单模块 | C45: 失败事务无脏数据 | D45: P0 | E45: 事务/集成 | F45: 库存不足或 CAS 冲突 | G45: 触发失败并查询订单/明细/库存 | H45: 库存不足场景 | I45: 复合操作整体回滚 | J45: OrderServiceIntegrationTest 通过 | K45: 通过 | M45: JUnit 集成测试 | N45: 2026-07-12
A46: TC-ORDER-011 | B46: 订单模块 | C46: 合法状态流转 | D46: P0 | E46: 状态机/集成 | F46: 准备各状态订单 | G46: 支付、发货、确认收货 | H46: PENDING->PAID->SHIPPED->COMPLETED | I46: 仅允许合法转换且无重复副作用 | J46: OrderServiceIntegrationTest 通过 | K46: 通过 | M46: JUnit 集成测试 | N46: 2026-07-12
A47: TC-ORDER-012 | B47: 订单模块 | C47: 直购缺失 quantity | D47: P0 | E47: 异常/接口 | F47: 已登录 | G47: POST /api/orders/direct 不传 quantity | H47: productId + 地址 | I47: 返回 400 | J47: 空值拆箱导致 HTTP 500 | K47: 失败 | L47: D-003 | M47: REST + 源码审计 | N47: 2026-07-12
A48: TC-ORDER-013 | B48: 订单模块 | C48: 下单显式 @Transactional 合规 | D48: P1 | E48: 静态合规 | F48: 阅读 OrderService | G48: 检查下单入口注解 | H48: AGENTS.md 5.2 | I48: 下单方法存在 @Transactional | J48: 实际使用 TransactionTemplate REQUIRES_NEW，无注解 | K48: 失败 | L48: D-010 | M48: 源码审计 | N48: 2026-07-12
A49: TC-ORDER-014 | B49: 订单模块 | C49: 订单明细快照 | D49: P0 | E49: 数据/集成 | F49: 创建订单 | G49: 检查 order_item | H49: 商品名和价格 | I49: 保存下单时快照，不受商品修改影响 | J49: 实体、DDL 和集成测试符合 | K49: 通过 | M49: 代码/SQL 审计 | N49: 2026-07-12
A50: TC-AI-001 | B50: AI助手 | C50: 健康检查与工具清单 | D50: P0 | E50: 服务/接口 | F50: Agent healthy | G50: GET /health | H50: 无 | I50: 200，llmEnabled=true，至少2工具 | J50: HTTP 200，8 个工具 | K50: 通过 | M50: REST 实测 | N50: 2026-07-12
A51: TC-AI-002 | B51: AI助手 | C51: 未认证调用 Agent | D51: P0 | E51: 安全/接口 | F51: 无 Token | G51: POST /agent/chat | H51: 任意消息 | I51: 返回 401 | J51: HTTP 401 | K51: 通过 | M51: REST 实测 | N51: 2026-07-12
A52: TC-AI-003 | B52: AI助手 | C52: 真实商品搜索推荐 | D52: P0 | E52: 工具调用 | F52: alice 已登录 | G52: 询问500元内编程键盘 | H52: “有没有适合敲代码的键盘，预算500” | I52: 调用商品工具并返回真实名称/库存 | J52: 返回 K87、静音键盘和真实库存 | K52: 通过 | M52: Agent 烟测 + 浏览器 | N52: 2026-07-12
A53: TC-AI-004 | B53: AI助手 | C53: 查询真实订单状态 | D53: P0 | E53: 工具调用 | F53: 用户有订单 | G53: 询问“我上次买的东西到哪了” | H53: alice JWT | I53: 调用 query_order_status | J53: 烟测 toolsUsed 包含订单工具 | K53: 通过 | M53: Agent 烟测 | N53: 2026-07-12
A54: TC-AI-005 | B54: AI助手 | C54: 长期偏好跨新会话 | D54: P0 | E54: 记忆 | F54: 用户表达机械键盘偏好 | G54: 新 session 请求推荐 | H54: session A/B | I54: 新会话仍体现偏好 | J54: 烟测通过，偏好 top3 可见 | K54: 通过 | M54: Agent 烟测 + 浏览器 | N54: 2026-07-12
A55: TC-AI-006 | B55: AI助手 | C55: 非购物问题拒答 | D55: P1 | E55: 安全/行为 | F55: Agent 可用 | G55: 询问天气 | H55: “今天天气怎么样” | I55: 说明仅支持购物，不编造 | J55: 烟测通过且未调用工具 | K55: 通过 | M55: Agent 烟测 | N55: 2026-07-12
A56: TC-AI-007 | B56: AI助手 | C56: 加购前二次确认 | D56: P0 | E56: 业务安全 | F56: 用户请求加购 | G56: 先提议、后发送“确认” | H56: 商品ID 1 | I56: 确认前不写购物车，确认后调用 add_to_cart | J56: 烟测通过 | K56: 通过 | M56: Agent 烟测 | N56: 2026-07-12
A57: TC-AI-008 | B57: AI助手 | C57: 待确认加购按 session 隔离 | D57: P0 | E57: 会话隔离 | F57: 同一用户两个 session | G57: A 发起加购，B 仅发送“确认” | H57: session A/B | I57: B 不应继承 A 的待确认状态 | J57: B 实际调用 add_to_cart 并成功加购 | K57: 失败 | L57: D-005 | M57: 定向运行测试 + main.py 审计 | N57: 2026-07-12
A58: TC-AI-009 | B58: AI助手 | C58: 商品对比工具稳定选择 | D58: P1 | E58: 非确定性 | F58: 真实 LLM 已启用 | G58: 执行完整 agent_smoke | H58: 对比商品ID1和2 | I58: toolsUsed 含 compare_products | J58: 首轮遗漏；同提示复测3/3和整套重跑通过 | K58: 失败 | L58: D-014 | M58: 真实模型烟测 | N58: 2026-07-12
A59: TC-AI-010 | B59: AI助手 | C59: 换账号后清理可见聊天 | D59: P0 | E59: 隐私/前端 | F59: Alice 已有聊天 | G59: SPA 内退出后 Bob 登录 | H59: Alice/Bob | I59: Bob 不可看到 Alice 消息 | J59: 模块级 messages 未在 logout 清理 | K59: 失败 | L59: D-006 | M59: 源码审计 | N59: 2026-07-12
A60: TC-AI-011 | B60: AI助手 | C60: Agent 401 自动刷新 | D60: P1 | E60: 认证/前端 | F60: Access 过期、Refresh 有效 | G60: 继续发起 Agent 请求 | H60: 过期 accessToken | I60: 刷新 Token 后重试或跳登录 | J60: agentApi/fetch 未挂统一响应刷新 | K60: 失败 | L60: D-007 | M60: 源码审计 | N60: 2026-07-12
A61: TC-AI-012 | B61: AI助手 | C61: 预算筛选覆盖完整结果 | D61: P1 | E61: 工具正确性 | F61: 符合预算商品排在第6名后 | G61: 调用 search_products(max_price) | H61: max_price=500 | I61: 搜索全集后按预算过滤 | J61: 仅取销量前5再过滤，可能漏商品 | K61: 失败 | L61: D-009 | M61: 源码审计 | N61: 2026-07-12
A62: TC-AI-013 | B62: AI助手 | C62: 会话历史读取 | D62: P1 | E62: 记忆/接口 | F62: 已有对话 | G62: GET /agent/history | H62: 合法 sessionId | I62: 返回 user/assistant 历史 | J62: Agent 烟测通过 | K62: 通过 | M62: Agent 烟测 | N62: 2026-07-12
A63: TC-AI-014 | B63: AI助手 | C63: 至少两个工具可调用 | D63: P0 | E63: 框架合规 | F63: Agent 启动 | G63: 检查工具注册与烟测 toolsUsed | H63: 无 | I63: 至少 search_products/query_order_status | J63: 实际注册8个工具且多工具烟测通过 | K63: 通过 | M63: 健康接口 + 烟测 | N63: 2026-07-12
A64: TC-DEP-001 | B64: 部署与文档 | C64: Compose 配置解析 | D64: P0 | E64: 部署 | F64: .env 已配置 | G64: 运行 docker compose config --quiet | H64: 当前 .env | I64: 命令成功 | J64: 退出码 0 | K64: 通过 | M64: Compose 实测 | N64: 2026-07-12
A65: TC-DEP-002 | B65: 部署与文档 | C65: 四服务健康状态 | D65: P0 | E65: 部署 | F65: Compose 已启动 | G65: 运行 docker compose ps | H65: frontend/backend/agent/mysql | I65: 全部 Up (healthy) | J65: 四服务 healthy，FailingStreak=0 | K65: 通过 | M65: Docker 实测 | N65: 2026-07-12
A66: TC-DEP-003 | B66: 部署与文档 | C66: 关键服务日志 | D66: P1 | E66: 可观测性 | F66: 业务与 Agent 已调用 | G66: 检查 backend/agent 日志 | H66: 并发和烟测时段 | I66: 有 INFO 业务日志且无 ERROR | J66: 订单成功/库存不足/工具调用可见，无 ERROR | K66: 通过 | M66: Docker logs | N66: 2026-07-12
A67: TC-DEP-004 | B67: 部署与文档 | C67: 后端自动化回归 | D67: P0 | E67: 自动化 | F67: JDK/Maven 可用 | G67: mvn.cmd -q test | H67: 9 个测试套件 | I67: 全部通过 | J67: 30 tests，0 failures，0 errors | K67: 通过 | M67: Surefire 报告 | N67: 2026-07-12
A68: TC-DEP-005 | B68: 部署与文档 | C68: 前端生产构建 | D68: P0 | E68: 构建 | F68: Node 依赖已安装 | G68: npm run build | H68: Vue3 项目 | I68: 构建成功 | J68: 2328 modules 构建成功；有 >500kB 警告 | K68: 通过 | L68: D-018 | M68: Vite build | N68: 2026-07-12
A69: TC-DEP-006 | B69: 部署与文档 | C69: Agent 完整烟测 | D69: P0 | E69: 自动化 | F69: 真实 LLM 与后端可用 | G69: 运行 scripts/agent_smoke.py | H69: 完整脚本 | I69: 所有场景通过 | J69: 重跑完整脚本通过，约78秒 | K69: 通过 | L69: D-014 | M69: Python 烟测 | N69: 2026-07-12
A70: TC-DEP-007 | B70: 部署与文档 | C70: 全新数据卷初始化 | D70: P1 | E70: 部署/数据库 | F70: 允许新建空卷 | G70: 从空卷 docker compose up -d --build | H70: 全新 mysql_data | I70: 自动执行 schema+seed 并健康 | J70: 本轮未破坏共享卷，未执行 | K70: 未执行 | M70: 风险控制 | N70: 2026-07-12
A71: TC-DEP-008 | B71: 部署与文档 | C71: Seed 数据规模 | D71: P1 | E71: 数据审计 | F71: 读取 docs/seed.sql | G71: 核对账号、分类和商品 | H71: Seed 文件 | I71: 至少3用户、3分类、20商品 | J71: 实际3用户、20分类节点、60商品 | K71: 通过 | M71: SQL 静态审计 | N71: 2026-07-12
A72: TC-DEP-009 | B72: 部署与文档 | C72: 核心表引擎和字符集 | D72: P1 | E72: 数据库合规 | F72: 读取 schema.sql | G72: 核对 CREATE TABLE | H72: 24张表 | I72: InnoDB、utf8mb4、外键合理 | J72: Schema 符合 | K72: 通过 | M72: SQL 静态审计 | N72: 2026-07-12
A73: TC-DEP-010 | B73: 部署与文档 | C73: ER 图覆盖全部表 | D73: P1 | E73: 文档合规 | F73: 读取 schema 与 ER | G73: 比较实体数量和字段 | H73: 24表 | I73: ER 展示全部表和关系 | J73: ER 仅19实体，缺5表及若干字段 | K73: 失败 | L73: D-011 | M73: 文档审计 | N73: 2026-07-12
A74: TC-DEP-011 | B74: 部署与文档 | C74: 数据库设计商品数量口径 | D74: P2 | E74: 文档一致性 | F74: 读取 seed 与 database-design | G74: 比较商品数量 | H74: Seed 60 | I74: 文档与 Seed 一致 | J74: 文档仍写45，实际60 | K74: 失败 | L74: D-012 | M74: 文档审计 | N74: 2026-07-12
A75: TC-DEP-012 | B75: 部署与文档 | C75: 外部端口符合项目规格 | D75: P1 | E75: 配置合规 | F75: 读取 AGENTS 与 Compose | G75: 比较宿主映射 | H75: backend 8080、MySQL 3306 | I75: 按规格映射或明确批准变更 | J75: 实际 backend 8081、MySQL 3307 | K75: 失败 | L75: D-013 | M75: 配置审计 | N75: 2026-07-12
A76: TC-DEP-013 | B76: 部署与文档 | C76: 前端自动化测试入口 | D76: P2 | E76: 自动化 | F76: 检查 package.json | G76: 运行/检查 test 脚本 | H76: 无 | I76: 存在基础组件/E2E 回归 | J76: 无 test/lint 脚本，本轮未执行 | K76: 未执行 | L76: D-016 | M76: 测试缺口 | N76: 2026-07-12
A77: TC-DEP-014 | B77: 部署与文档 | C77: Agent 确定性单元测试 | D77: P1 | E77: 自动化 | F77: 检查 agent-service | G77: pytest 收集 | H77: pytest | I77: 覆盖工具授权、会话隔离、偏好 upsert | J77: collected 0 items | K77: 未执行 | L77: D-017 | M77: pytest 实测 | N77: 2026-07-12
A78: TC-DEP-015 | B78: 部署与文档 | C78: Swagger 页面可访问 | D78: P1 | E78: 文档/接口 | F78: backend healthy | G78: GET /swagger-ui/index.html | H78: 宿主 8081 | I78: 返回 200 页面 | J78: Springdoc 已配置，运行服务可访问 | K78: 通过 | M78: 配置 + 服务检查 | N78: 2026-07-12

Sheet 环境与账号
A1: 测试环境与账号
A2: 所有密钥仅检查是否配置，不在工作簿中记录值；账号仅限本机演示数据库
A4: 1. 服务与运行环境
A5: 组件 | B5: 技术/版本 | C5: 宿主地址 | D5: 容器地址/端口 | E5: 状态 | F5: 验证方式
A6: 操作系统 | B6: Windows / Asia-Shanghai | C6: 本机 | D6: — | E6: 可用 | F6: 当前 Codex 工作区
A7: 前端 | B7: Vue 3 + Nginx 1.27 | C7: http://127.0.0.1/ | D7: frontend:80 | E7: Healthy | F7: 浏览器首页与健康检查
A8: 后端 | B8: Spring Boot 3.3.6 / Java 17 | C8: http://127.0.0.1:8081 | D8: backend:8080 | E8: Healthy | F8: 公开商品接口/Swagger
A9: Agent | B9: FastAPI + LangChain / Python 3.11 | C9: http://127.0.0.1:8000 | D9: agent-service:8000 | E9: Healthy | F9: GET /health
A10: MySQL | B10: MySQL 8.0 | C10: 127.0.0.1:3307 | D10: mysql:3306 | E10: Healthy | F10: mysqladmin ping
A11: Docker | B11: Engine 29.6.1 / Compose 5.2.0 | C11: 本机 Docker Desktop | D11: Compose network | E11: Healthy | F11: docker compose ps
A12: 浏览器 | B12: Codex 应用内浏览器 | C12: http://127.0.0.1/ | D12: — | E12: 可用 | F12: DOM 快照与控制台日志
A13: 构建 | B13: Maven 3.9.16 / JDK 17 / Node 20 image | C13: 本机/容器 | D13: — | E13: 可用 | F13: mvn test / npm run build
A15: 2. 环境变量（只记录用途和配置状态）
A16: 变量 | B16: 服务 | C16: 用途 | D16: 是否必填 | E16: 本轮状态 | F16: 安全说明
A17: MYSQL_ROOT_PASSWORD | B17: MySQL/Backend/Agent | C17: 数据库 root 密码 | D17: 是 | E17: 已配置 | F17: 值不写入测试文档和 Git
A18: MYSQL_DATABASE | B18: 全部 | C18: 数据库名 | D18: 是 | E18: 已配置 | F18: smart_mall
A19: JWT_SECRET | B19: Backend | C19: JWT 签名，至少32字符 | D19: 是 | E19: 已配置 | F19: 值不披露
A20: INTERNAL_SERVICE_SECRET | B20: Backend/Agent | C20: 服务间认证 | D20: 是 | E20: 已配置 | F20: 值不披露
A21: LLM_API_KEY | B21: Agent | C21: 真实模型调用 | D21: 真实模型演示必填 | E21: 已配置 | F21: 值不披露
A22: LLM_BASE_URL | B22: Agent | C22: OpenAI 兼容端点 | D22: 按供应商 | E22: 已配置 | F22: 值不披露
A23: LLM_MODEL | B23: Agent | C23: 模型名称 | D23: 否 | E23: 已配置 | F23: 健康接口显示 llmEnabled=true
A25: 3. 测试账号
A26: 账号 | B26: 密码 | C26: 角色 | D26: 手机 | E26: 用途 | F26: 数据来源 | G26: 注意事项
A27: admin | B27: 123456 | C27: ADMIN | D27: 13800000000 | E27: 管理后台、商品管理、图片上传 | F27: Seed SQL | G27: 仅本机演示；禁止复用到生产
A28: alice | B28: 123456 | C28: USER | D28: 13800000001 | E28: 购物车、订单、偏好、AI 对话 | F28: Seed SQL | G28: 包含预置购物车、订单和偏好
A29: bob | B29: 123456 | C29: USER | D29: 13800000002 | E29: 用户隔离、换账号场景 | F29: Seed SQL | G29: 用于跨用户可见性检查
A30: smoke_rt_815a93bda8 | B30: 脚本生成 | C30: USER | D30: 脚本随机 | E30: 隔离订单链路 | F30: 本轮运行态测试 | G30: 订单377已取消，库存已回补
A31: race_1783841014-1-dcd4daa502 | B31: 脚本生成 | C31: USER | D31: 脚本随机 | E31: 100/80并发验收 | F31: 并发脚本 | G31: 商品66库存0，保留作证据
A33: 4. 测试命令与入口
A34: 用途 | B34: 命令/入口 | C34: 本轮结果 | D34: 证据位置
A35: 后端自动化 | B35: cd backend; mvn.cmd -q test | C35: 30/30 通过 | D35: backend/target/surefire-reports
A36: 前端构建 | B36: cd frontend; npm.cmd run build | C36: 构建通过，存在大 chunk 警告 | D36: frontend/dist
A37: Agent 烟测 | B37: python scripts/agent_smoke.py --base-url http://127.0.0.1:8000 --backend-url http://127.0.0.1:8081 | C37: 首轮1项间歇失败，整套重跑通过 | D37: Agent/Backend logs
A38: 并发测试 | B38: python scripts/concurrent_order_test.py --base-url http://127.0.0.1:8081 --rounds 1 --requests 100 --stock 80 | C38: 80成功/20库存不足/0异常 | D38: 数据库+脚本输出
A39: 容器状态 | B39: docker compose ps | C39: 四服务 healthy | D39: Docker Desktop
A40: 前端入口 | B40: http://127.0.0.1/ | C40: 可访问 | D40: Codex 应用内浏览器
A41: Swagger | B41: http://127.0.0.1:8081/swagger-ui/index.html | C41: 可访问 | D41: Springdoc

Sheet 缺陷登记
A1: 缺陷登记
A2: 当前周期缺陷在前；历史已关闭项来自 docs/bug-list.md，用于展示缺陷生命周期
A4: 缺陷ID | B4: 模块 | C4: 标题 | D4: 严重度 | E4: 优先级 | F4: 状态 | G4: 发现方式 | H4: 复现步骤 | I4: 预期 | J4: 实际 | K4: 证据/位置 | L4: 修复建议 | M4: 关联用例 | N4: 复测结论
A5: D-001 | B5: 订单/前端 | C5: 结算页运行时空白 | D5: 阻断 | E5: P0 | F5: 新建 | G5: 浏览器 | H5: alice 购物车点击“去结算” | I5: 结算页展示商品、地址和提交按钮 | J5: 页面空白，控制台 ReferenceError: reactive is not defined | K5: frontend/src/views/CheckoutView.vue:118,136 | L5: 从 vue 导入 reactive，补路由级组件测试 | M5: TC-ORDER-003 | N5: 待修复后复测
A6: D-002 | B6: 安全/商品 | C6: 匿名管理员商品列表返回403而非401 | D6: 高 | E6: P1 | F6: 新建 | G6: REST | H6: 无 Token GET /api/products/admin | I6: 返回401 | J6: 返回403 | K6: SecurityConfig.java:43；ProductController.java:95 | L6: 从游客 products GET 白名单中排除 admin 路径 | M6: TC-AUTH-010 | N6: 未修复
A7: D-003 | B7: 接口校验 | C7: 缺失或类型错误参数返回500 | D7: 高 | E7: P1 | F7: 新建 | G7: REST/源码 | H7: 缺 password、缺 quantity、page=abc、非法路径ID | I7: 统一返回400 | J7: 多处返回500 | K7: ApiSupport.java；Auth/Cart/Order 请求DTO | L7: 补 @NotNull/@NotBlank 和类型转换异常处理 | M7: TC-AUTH-007,TC-PROD-012,TC-CART-005,TC-ORDER-012 | N7: 未修复
A8: D-004 | B8: 服务间认证 | C8: 内部接口缺认证头返回500 | D8: 高 | E8: P1 | F8: 新建 | G8: REST | H8: 不带 X-Internal-Service/Secret 请求内部订单接口 | I8: 返回401/403 | J8: MissingRequestHeaderException 被映射为500 | K8: OrderController.java:164-189；ApiSupport.java:257 | L8: 显式校验头或映射缺头异常 | M8: — | N8: 未修复
A9: D-005 | B9: AI助手 | C9: 待确认加购状态未按 session 隔离 | D9: 高 | E9: P1 | F9: 新建 | G9: 定向测试 | H9: 同用户 A 发起加购，B 只发送“确认” | I9: B 不继承 A 的待确认动作 | J9: B 调用 add_to_cart 并写入购物车 | K9: agent-service/app/main.py:912-929,1528-1532 | L9: 状态键加入 sessionId，补跨会话测试 | M9: TC-AI-008 | N9: 已复现，未修复
A10: D-006 | B10: AI前端 | C10: 换账号后可能保留前一用户聊天 | D10: 高 | E10: P1 | F10: 新建 | G10: 源码审计 | H10: Alice 对话后 SPA 登出，再登录 Bob | I10: 清空消息/session/loadedSessions | J10: logout 未重置模块级会话状态 | K10: useAgentConversation.js:7-16,70-76；store.js:58-66 | L10: 登出时统一 reset Agent 会话状态 | M10: TC-AI-010 | N10: 待浏览器复测
A11: D-007 | B11: AI前端 | C11: Agent 请求 401 不触发统一刷新 | D11: 中 | E11: P2 | F11: 新建 | G11: 源码审计 | H11: Access 过期、Refresh 有效时调用 Agent | I11: 刷新并重试或跳登录 | J11: agentApi 和原生 fetch 仅显示通用错误 | K11: frontend/src/api/http.js:20-67；useAgentConversation.js:121-169 | L11: 复用主 API 单飞 refresh 逻辑 | M11: TC-AI-011 | N11: 未修复
A12: D-008 | B12: 搜索 | C12: 搜索结果排序控件无效 | D12: 中 | E12: P2 | F12: 新建 | G12: 源码审计 | H12: 搜索键盘后切换价格升/降序 | I12: 请求带 sort 且列表变化 | J12: 搜索请求未传 sort，后端固定销量排序 | K12: ProductListView.vue:280-283,331 | L12: 搜索接口支持 sort 并透传 | M12: TC-PROD-007 | N12: 未修复
A13: D-009 | B13: AI工具 | C13: 预算过滤可能漏掉第6名后的商品 | D13: 中 | E13: P2 | F13: 新建 | G13: 源码审计 | H13: 符合预算商品不在销量前5时搜索 | I13: 返回所有候选中的预算内商品 | J13: 先 size=5 后本地过滤 | K13: main.py:569-575 | L13: 将 maxPrice 下推后端或扩大后再截断 | M13: TC-AI-012 | N13: 未修复
A14: D-010 | B14: 订单合规 | C14: 下单入口没有显式 @Transactional | D14: 中 | E14: P2 | F14: 新建 | G14: 静态审计 | H14: 检查 OrderService create/createDirect | I14: 符合 AGENTS.md 明确注解要求 | J14: 使用 TransactionTemplate REQUIRES_NEW | K14: OrderService.java:51-59,108-112 | L14: 调整事务重试边界并保留显式注解 | M14: TC-ORDER-013 | N14: 功能正确但合规未满足
A15: D-011 | B15: 数据库文档 | C15: ER 图缺少5张表及部分字段 | D15: 中 | E15: P2 | F15: 新建 | G15: 文档审计 | H15: 比较 schema.sql 与 er-diagram.md | I15: 24表全部呈现 | J15: ER仅19实体，缺coupon等5表 | K15: ER diagram 与 schema.sql | L15: 补齐实体、外键、points/discount 字段 | M15: TC-DEP-010 | N15: 未修复
... A40: B017 | B40: 商品 | C40: 缺少本地图片上传 | D40: 中 | E40: P1 | F40: 已关闭 | G40: 历史缺陷 | H40: 管理员上传PNG | I40: 201并可读取 | J40: 曾仅支持URL | K40: docs/bug-list.md | L40: 新增上传接口与静态映射 | M40: TC-PROD-011 | N40: 已关闭

Sheet 测试数据
A1: 测试数据
A2: 基线来自 docs/seed.sql；运行脚本生成的数据与 Seed 分开记录，避免误认为干净基线
A4: 1. Seed 账号
A5: 用户ID | B5: 用户名 | C5: 角色 | D5: 手机号 | E5: 初始积分 | F5: 密码哈希 | G5: 明文测试密码 | H5: 用途
A6: 1 | B6: admin | C6: ADMIN | D6: 13800000000 | E6: 0 | F6: $2a$10$... | G6: 123456 | H6: 管理权限
A7: 2 | B7: alice | C7: USER | D7: 13800000001 | E7: 300 | F7: $2a$10$... | G7: 123456 | H7: 购物/订单/偏好
A8: 3 | B8: bob | C8: USER | D8: 13800000002 | E8: 120 | F8: $2a$10$... | G8: 123456 | H8: 隔离测试
A10: 2. 分类基线（20个分类节点）
A11: ID | B11: 分类名称 | C11: 父级ID | D11: 层级 | E11: 排序
A12: 1 | B12: 数码电子 | D12: 一级 | E12: 1
A13: 2 | B13: 电脑办公 | D13: 一级 | E13: 2
A14: 3 | B14: 家居生活 | D14: 一级 | E14: 3
A15: 4 | B15: 键盘鼠标 | C15: 2 | D15: 二级 | E15: 1
A16: 5 | B16: 手机配件 | C16: 1 | D16: 二级 | E16: 2
A17: 6 | B17: 智能家居 | C17: 3 | D17: 二级 | E17: 1
A18: 7 | B18: 服饰鞋包 | D18: 一级 | E18: 4
A19: 8 | B19: 美妆个护 | D19: 一级 | E19: 5
A20: 9 | B20: 运动户外 | D20: 一级 | E20: 6
A21: 10 | B21: 图书文创 | D21: 一级 | E21: 7
A22: 11 | B22: 厨房餐具 | C22: 3 | D22: 二级 | E22: 2
A23: 12 | B23: 母婴用品 | C23: 3 | D23: 二级 | E23: 3
A24: 13 | B24: 男装女装 | C24: 7 | D24: 二级 | E24: 1
A25: 14 | B25: 鞋靴箱包 | C25: 7 | D25: 二级 | E25: 2
A26: 15 | B26: 护肤彩妆 | C26: 8 | D26: 二级 | E26: 1
A27: 16 | B27: 个人护理 | C27: 8 | D27: 二级 | E27: 2
A28: 17 | B28: 健身装备 | C28: 9 | D28: 二级 | E28: 1
A29: 18 | B29: 户外露营 | C29: 9 | D29: 二级 | E29: 2
A30: 19 | B30: 技术图书 | C30: 10 | D30: 二级 | E30: 1
A31: 20 | B31: 文具手账 | C31: 10 | D31: 二级 | E31: 2
A33: 3. 代表性商品基线
A34: 商品ID | B34: 分类ID | C34: 商品名称 | D34: 价格 | E34: 库存 | F34: 销量 | G34: 状态 | H34: 版本 | I34: 测试用途
A35: 1 | B35: 4 | C35: 极客机械键盘 K87 | D35: 399 | E35: 80 | F35: 320 | G35: 上架 | H35: 0 | I35: 搜索/AI/订单快照
A36: 2 | B36: 4 | C36: 静音办公机械键盘 | D36: 459 | E36: 45 | F36: 210 | G36: 上架 | H36: 0 | I36: AI 对比/预算
A37: 3 | B37: 4 | C37: 电竞鼠标 M9 | D37: 199 | E37: 120 | F37: 500 | G37: 上架 | H37: 0 | I37: 销量排序
A38: 4 | B38: 2 | C38: 27 英寸 4K 显示器 | D38: 1699 | E38: 35 | F38: 96 | G38: 上架 | H38: 0 | I38: 高价边界
A39: 5 | B39: 2 | C39: 轻薄办公笔记本 | D39: 5299 | E39: 25 | F39: 88 | G39: 上架 | H39: 0 | I39: 高价边界
A40: 6 | B40: 1 | C40: 降噪蓝牙耳机 | D40: 699 | E40: 60 | F40: 260 | G40: 上架 | H40: 0 | I40: 通用搜索
A41: 7 | B41: 1 | C41: 运动智能手表 | D41: 899 | E41: 50 | F41: 150 | G41: 上架 | H41: 0 | I41: 分类过滤
A42: 8 | B42: 5 | C42: 65W 氮化镓充电器 | D42: 129 | E42: 150 | F42: 410 | G42: 上架 | H42: 0 | I42: 购物车预置
A43: 9 | B43: 5 | C43: 编织数据线套装 | D43: 39 | E43: 300 | F43: 800 | G43: 上架 | H43: 0 | I43: 首页热销
A44: 10 | B44: 6 | C44: 智能台灯 Pro | D44: 259 | E44: 70 | F44: 170 | G44: 上架 | H44: 0 | I44: 描述搜索
A45: 11 | B45: 6 | C45: 智能插座 Mini | D45: 59 | E45: 180 | F45: 390 | G45: 上架 | H45: 0 | I45: 分页/排序
A46: 12 | B46: 3 | C46: 人体工学椅 | D46: 799 | E46: 32 | F46: 90 | G46: 上架 | H46: 0 | I46: 库存边界
... A55: 21 | B55: 2 | C55: 抢购测试商品 | D55: 9.9 | E55: 80 | F55: 0 | G55: 上架 | H55: 0 | I55: 100/80并发基线
A57: 4. 边界与异常数据
A58: 数据集ID | B58: 对象 | C58: 输入 | D58: 边界/等价类 | E58: 期望 | F58: 关联用例
A59: TD-B001 | B59: 注册密码 | C59: 12345 | D59: 长度<6 | E59: 400 | F59: TC-AUTH-006
A60: TD-B002 | B60: 注册密码 | C60: 缺失字段 | D60: Null | E60: 400（当前500） | F60: TC-AUTH-007
A61: TD-B003 | B61: 登录密码 | C61: wrong-password | D61: 错误凭证 | E61: 401统一文案 | F61: TC-AUTH-003
A62: TD-B004 | B62: 页码 | C62: 999 | D62: 超过最大页 | E62: 200空列表 | F62: TC-PROD-004
A63: TD-B005 | B63: 页码 | C63: abc | D63: 非法类型 | E63: 400（当前500） | F63: TC-PROD-012
A64: TD-B006 | B64: 搜索词 | C64: 键盘 | D64: 正常中文 | E64: 命中5条 | F64: TC-PROD-003
A65: TD-B007 | B65: 搜索词 | C65: “ 键盘 ” | D65: 前后空格 | E65: trim后命中（当前0） | F65: TC-PROD-008
A66: TD-B008 | B66: 商品价格 | C66: 0 | D66: 非正数 | E66: 400 | F66: TC-PROD-009
A67: TD-B009 | B67: 商品库存 | C67: -1 | D67: 负数 | E67: 400 | F67: TC-PROD-010
A68: TD-B010 | B68: 购物数量 | C68: 0/-1 | D68: 非法数量 | E68: 400 | F68: TC-CART-004
A69: TD-B011 | B69: 购物数量 | C69: 缺失 | D69: Null | E69: 400（当前500） | F69: TC-CART-005
... A72: TD-B014 | B72: Agent问题 | C72: 今天天气怎么样 | D72: 非购物域 | E72: 礼貌拒答 | F72: TC-AI-006
A74: 5. 本轮运行夹具与结果
A75: 类型 | B75: 标识 | C75: 用户/商品/订单 | D75: 关键输入 | E75: 最终状态 | F75: 用途/保留策略
A76: 隔离订单 | B76: 运行态 smoke | C76: userId=9 / productId=21 / orderId=377 | D76: 数量1、地址测试 | E76: 订单 CANCELLED，库存80 | F76: 验证创建、非法确认、取消和回补；保留证据
A77: 并发轮次 | B77: 1783841014-1-dcd4daa502 | C77: userId=10 / productId=66 / 80订单 | D77: 100请求、库存80 | E77: stock=0,sales=80,version=80 | F77: 验证无超卖；脚本策略保留
A78: Agent偏好 | B78: alice | C78: 机械键盘、预算敏感、办公学习 | D78: 跨新session | E78: weight=2.0 | F78: 验证长期记忆
A79: Agent对比 | B79: 商品1与2 | C79: K87 / 静音办公键盘 | D79: 真实模型 | E79: 首轮工具名遗漏，复测通过 | F79: 记录非确定性风险

Sheet 测试报告
A1: 智能商城测试报告
A2: 测试日期 2026-07-12；统计由“测试用例”和“缺陷登记”公式联动
A4: 用例总数 | B4: =COUNTA('测试用例'!$A$5:$A$200) -> 74 | C4: 通过 | D4: =COUNTIF('测试用例'!$K$5:$K$200,"通过") -> 54 | E4: 失败 | F4: =COUNTIF('测试用例'!$K$5:$K$200,"失败") -> 17 | G4: 未执行 | H4: =COUNTIF('测试用例'!$K$5:$K$200,"未执行") -> 3
A5: 严格通过率 | B5: =IF((B4-H4)=0,0,D4/(B4-H4)) -> 0.76056338 | C5: 阻断未关闭 | D5: =COUNTIFS('缺陷登记'!$D$5:$D$80,"阻断",'缺陷登记'!$F$5:$F$80,"<>已关闭") -> 1 | E5: 高严重度未关闭 | F5: =COUNTIFS('缺陷登记'!$D$5:$D$80,"高",'缺陷登记'!$F$5:$F$80,"<>已关闭") -> 5 | G5: 准出结论 | H5: 不通过
A7: 1. 模块执行概览
A8: 模块 | B8: 用例数 | C8: 通过 | D8: 失败 | E8: 阻塞 | F8: 未执行 | G8: 通过率 | H8: 说明
A9: 用户模块 | B9: =COUNTIF('测试用例'!$B$5:$B$200,A9) -> 11 | C9: =COUNTIFS('测试用例'!$B$5:$B$200,A9,'测试用例'!$K$5:$K$200,"通过") -> 9 | D9: =COUNTIFS('测试用例'!$B$5:$B$200,A9,'测试用例'!$K$5:$K$200,"失败") -> 2 | E9: =COUNTIFS('测试用例'!$B$5:$B$200,A9,'测试用例'!$K$5:$K$200,"阻塞") -> 0 | F9: =COUNTIFS('测试用例'!$B$5:$B$200,A9,'测试用例'!$K$5:$K$200,"未执行") -> 0 | G9: =IF((B9-F9)=0,0,C9/(B9-F9)) -> 0.81818182 | H9: 注册、JWT、权限
A10: 商品与搜索 | B10: =COUNTIF('测试用例'!$B$5:$B$200,A10) -> 12 | C10: =COUNTIFS('测试用例'!$B$5:$B$200,A10,'测试用例'!$K$5:$K$200,"通过") -> 9 | D10: =COUNTIFS('测试用例'!$B$5:$B$200,A10,'测试用例'!$K$5:$K$200,"失败") -> 3 | E10: =COUNTIFS('测试用例'!$B$5:$B$200,A10,'测试用例'!$K$5:$K$200,"阻塞") -> 0 | F10: =COUNTIFS('测试用例'!$B$5:$B$200,A10,'测试用例'!$K$5:$K$200,"未执行") -> 0 | G10: =IF((B10-F10)=0,0,C10/(B10-F10)) -> 0.75 | H10: 分页、搜索、校验
A11: 购物车 | B11: =COUNTIF('测试用例'!$B$5:$B$200,A11) -> 8 | C11: =COUNTIFS('测试用例'!$B$5:$B$200,A11,'测试用例'!$K$5:$K$200,"通过") -> 7 | D11: =COUNTIFS('测试用例'!$B$5:$B$200,A11,'测试用例'!$K$5:$K$200,"失败") -> 1 | E11: =COUNTIFS('测试用例'!$B$5:$B$200,A11,'测试用例'!$K$5:$K$200,"阻塞") -> 0 | F11: =COUNTIFS('测试用例'!$B$5:$B$200,A11,'测试用例'!$K$5:$K$200,"未执行") -> 0 | G11: =IF((B11-F11)=0,0,C11/(B11-F11)) -> 0.875 | H11: 数量、库存、前端合计
A12: 订单模块 | B12: =COUNTIF('测试用例'!$B$5:$B$200,A12) -> 14 | C12: =COUNTIFS('测试用例'!$B$5:$B$200,A12,'测试用例'!$K$5:$K$200,"通过") -> 11 | D12: =COUNTIFS('测试用例'!$B$5:$B$200,A12,'测试用例'!$K$5:$K$200,"失败") -> 3 | E12: =COUNTIFS('测试用例'!$B$5:$B$200,A12,'测试用例'!$K$5:$K$200,"阻塞") -> 0 | F12: =COUNTIFS('测试用例'!$B$5:$B$200,A12,'测试用例'!$K$5:$K$200,"未执行") -> 0 | G12: =IF((B12-F12)=0,0,C12/(B12-F12)) -> 0.78571429 | H12: 事务、状态机、100/80并发
A13: AI助手 | B13: =COUNTIF('测试用例'!$B$5:$B$200,A13) -> 14 | C13: =COUNTIFS('测试用例'!$B$5:$B$200,A13,'测试用例'!$K$5:$K$200,"通过") -> 9 | D13: =COUNTIFS('测试用例'!$B$5:$B$200,A13,'测试用例'!$K$5:$K$200,"失败") -> 5 | E13: =COUNTIFS('测试用例'!$B$5:$B$200,A13,'测试用例'!$K$5:$K$200,"阻塞") -> 0 | F13: =COUNTIFS('测试用例'!$B$5:$B$200,A13,'测试用例'!$K$5:$K$200,"未执行") -> 0 | G13: =IF((B13-F13)=0,0,C13/(B13-F13)) -> 0.64285714 | H13: 工具、订单、记忆、隔离
A14: 部署与文档 | B14: =COUNTIF('测试用例'!$B$5:$B$200,A14) -> 15 | C14: =COUNTIFS('测试用例'!$B$5:$B$200,A14,'测试用例'!$K$5:$K$200,"通过") -> 9 | D14: =COUNTIFS('测试用例'!$B$5:$B$200,A14,'测试用例'!$K$5:$K$200,"失败") -> 3 | E14: =COUNTIFS('测试用例'!$B$5:$B$200,A14,'测试用例'!$K$5:$K$200,"阻塞") -> 0 | F14: =COUNTIFS('测试用例'!$B$5:$B$200,A14,'测试用例'!$K$5:$K$200,"未执行") -> 3 | G14: =IF((B14-F14)=0,0,C14/(B14-F14)) -> 0.75 | H14: Compose、构建、Schema、文档
A16: 2. 关键执行证据
A17: 检查项 | B17: 结果 | C17: 实际证据 | D17: 判定
A18: 后端自动化 | B18: 30 tests / 0 failures / 0 errors | C18: 9个 Surefire 套件全部通过 | D18: 通过
A19: 前端生产构建 | B19: 2328 modules | C19: 构建成功；存在 >500kB chunk 警告 | D19: 通过（有风险）
A20: Docker Compose | B20: 四服务 healthy | C20: frontend80、backend8081、agent8000、mysql3307 | D20: 通过
A21: 并发库存 | B21: 100请求 / 80库存 | C21: 成功80、库存不足20、unexpected0、stock0、sales80、version80 | D21: 通过
A22: Agent 完整烟测 | B22: 整套重跑通过 | C22: 商品、方案、详情、对比、订单、记忆、加购、拒答 | D22: 通过（首轮不稳定）
A23: 浏览器主链路 | B23: 登录/搜索/购物车/订单/AI可用 | C23: 结算页因 reactive 未导入空白 | D23: 失败
A24: 数据库/文档 | B24: Schema 24表、Seed 60商品 | C24: ER少5表，数据库设计数量过期 | D24: 失败
A26: 3. 主要缺陷与风险
A27: 级别 | B27: 问题 | C27: 影响 | D27: 当前处置 | E27: 发布建议
A28: 阻断 | B28: 结算页 reactive 未导入 | C28: 购物车结算和立即购买主链路不可用 | D28: D-001 新建 | E28: 必须修复并浏览器复测
A29: 高 | B29: Agent 待确认加购跨 session | C29: 可能在错误会话执行写操作 | D29: D-005 新建 | E29: 必须隔离并补确定性测试
A30: 高 | B30: 换账号聊天状态未清理 | C30: 存在跨用户可见性/隐私风险 | D30: D-006 新建 | E30: 必须在 logout reset
A31: 高 | B31: 缺失/非法参数返回500 | C31: 暴露服务内部错误且不符合接口规范 | D31: D-003 新建 | E31: 统一校验和400映射
A32: 中 | B32: 真实模型工具选择非确定性 | C32: 答辩脚本可能偶发失败 | D32: D-014 调查中 | E32: 约束路由并保留重试/证据
A33: 中 | B33: ER和端口与规格不一致 | C33: 静态验收或答辩可能扣分 | D33: D-011/D-013 | E33: 修正文档或统一配置
A34: 风险 | B34: 未从全新 MySQL 卷重建 | C34: 一键启动的干净环境复现尚未验证 | D34: 用例未执行 | E34: 答辩前使用隔离卷补测
A36: 4. 结论与复测门槛
A37: 当前结论 | B37: 不通过：核心后端、并发与AI能力基本可用，但结算主链路存在阻断缺陷，且有两项高严重度会话隔离问题。
A38: 修复优先级 | B38: P0：D-001；P1：D-002/D-003/D-004/D-005/D-006；其余按答辩风险排序。
A39: 必须复测 | B39: 购物车结算、立即购买、创建并支付订单；Alice/Bob 聊天隔离；跨 session 加购确认；异常参数400。
A40: 回归要求 | B40: 后端30测试保持全绿；100/80并发再次得到80/20；Agent完整烟测连续通过；四服务保持healthy。
A41: 准出条件 | B41: 阻断和高严重度缺陷全部关闭；五大模块浏览器主链路可演示；全新数据卷启动验证通过。
